{
  "symbol": "BTC",
  "name": "Bitcoin",
  "price": 71073,
  "change_24h": -2.27,
  "market_cap": 1422654326000.0366,
  "rsi": 46.84,
  "analysis": {
    "elliott_wave": "Currently in a corrective wave (4) within a larger bearish trend, potentially setting up for a wave 5 decline.",
    "momentum": "The RSI is neutral at 46.84, indicating a lack of clear momentum, but the recent price action suggests a bearish trend continuation.",
    "key_levels": {
      "support": [
        "$69,000",
        "$67,500"
      ],
      "resistance": [
        "$72,000",
        "$74,000"
      ]
    },
    "trend_bias": "bearish",
    "trade_plan": "Consider shorting with a stop-loss above $72,000, targeting $69,000 or lower. Monitor the RSI for signs of oversold conditions. Be cautious of a potential bounce.",
    "risk_note": "A sudden shift in investor sentiment could lead to a sharp price reversal."
  },
  "updated_at": "2026-04-12T14:31:58.052600+00:00"
}