{
  "symbol": "BTC",
  "name": "Bitcoin",
  "price": 66464,
  "change_24h": -0.72,
  "market_cap": 1329965192456.6814,
  "rsi": 34.04,
  "analysis": {
    "elliott_wave": "BTC is currently in a corrective wave 2, with a potential for a larger wave 4 forming before a potential wave 5.",
    "momentum": "The neutral RSI reading suggests a lack of clear momentum, but the recent price action indicates a slight bearish bias.",
    "key_levels": {
      "support": [
        "$65,000",
        "$63,000"
      ],
      "resistance": [
        "$67,000",
        "$69,000"
      ]
    },
    "trend_bias": "neutral",
    "trade_plan": "Consider shorting on a break below $65,000, with a target of $63,000. Alternatively, look for a bounce to $67,000 for a potential long opportunity. Monitor the price action closely for a clear trend direction.",
    "risk_note": "A break above $69,000 could invalidate the current neutral trend bias and indicate a strong bullish trend"
  },
  "updated_at": "2026-03-29T15:58:48.111921+00:00"
}