{
  "symbol": "BTC",
  "name": "Bitcoin",
  "price": 66862,
  "change_24h": 0.94,
  "market_cap": 1336784440384.0898,
  "rsi": 40.9,
  "analysis": {
    "elliott_wave": "BTC is likely in a corrective wave (B) within a larger bull trend, as price action suggests a potential retest of the recent highs.",
    "momentum": "Momentum is neutral, with a slight upward bias, as the RSI is at 40.9 and price action is consolidating.",
    "key_levels": {
      "support": [
        "$64,000",
        "$62,000"
      ],
      "resistance": [
        "$68,000",
        "$70,000"
      ]
    },
    "trend_bias": "bullish",
    "trade_plan": "Buy on dips to $64,000, targeting $68,000. Set stop-loss at $62,000. Monitor for potential breakouts above $70,000.",
    "risk_note": "A sudden shift in investor sentiment could lead to a sharp decline in price, potentially breaking below $62,000."
  },
  "updated_at": "2026-04-03T14:26:52.275243+00:00"
}