{
  "symbol": "BTC",
  "name": "Bitcoin",
  "price": 66983,
  "change_24h": -1.74,
  "market_cap": 1340497282467.278,
  "rsi": 53.3,
  "analysis": {
    "elliott_wave": "BTC is currently in a corrective wave, potentially forming a double bottom pattern. The wave count suggests a potential reversal in the coming days.",
    "momentum": "The RSI reading of 53.3 indicates a neutral momentum, with neither strong buying nor selling pressure. However, the recent 1.74% price drop suggests a slight bearish bias.",
    "key_levels": {
      "support": [
        "$64,500",
        "$62,000"
      ],
      "resistance": [
        "$67,500",
        "$69,000"
      ]
    },
    "trend_bias": "neutral",
    "trade_plan": "Consider buying on a bounce above $67,500, targeting $69,000. Alternatively, sell on a break below $64,500, aiming for $62,000. Monitor the price action closely for a potential reversal.",
    "risk_note": "A break below $62,000 could lead to a more significant price drop, potentially targeting $58,000."
  },
  "updated_at": "2026-04-02T23:04:02.758559+00:00"
}