{
  "symbol": "BTC",
  "name": "Bitcoin",
  "price": 74751,
  "change_24h": 3.54,
  "market_cap": 1496225324459.0835,
  "rsi": 77.15,
  "analysis": {
    "elliott_wave": "BTC is currently in a potential 5th wave of the larger bull trend, with a possible ending diagonal pattern forming.",
    "momentum": "Momentum is strong, but RSI is overbought, suggesting a potential pullback or consolidation is due.",
    "key_levels": {
      "support": [
        "$70,000",
        "$68,000"
      ],
      "resistance": [
        "$80,000",
        "$82,000"
      ]
    },
    "trend_bias": "bullish",
    "trade_plan": "Consider scaling into long positions on a pullback to $70,000-$72,000, with a target of $82,000. Monitor for a potential bearish reversal if price fails to hold above $70,000.",
    "risk_note": "Key risk is a potential sharp correction if the ending diagonal pattern fails to form, leading to a retest of $60,000."
  },
  "updated_at": "2026-04-14T17:09:20.433972+00:00"
}