{
  "symbol": "BTC",
  "name": "Bitcoin",
  "price": 75526,
  "change_24h": -0.89,
  "market_cap": 1512151927222.6213,
  "rsi": 57.48,
  "analysis": {
    "elliott_wave": "BTC is likely in a corrective wave (B) within a larger bull trend, as price action has been forming a series of higher lows.",
    "momentum": "Momentum is neutral, with RSI at 57.48, indicating a pause in the downtrend, but a clear break above 60 would be needed to confirm a shift in momentum.",
    "key_levels": {
      "support": [
        "$73,000",
        "$70,000"
      ],
      "resistance": [
        "$76,000",
        "$78,000"
      ]
    },
    "trend_bias": "neutral",
    "trade_plan": "Consider buying on a break above $76,000, targeting $80,000, but be cautious of a potential breakdown below $73,000.",
    "risk_note": "A break below $70,000 could signal a more significant downtrend."
  },
  "updated_at": "2026-04-19T12:33:33.485601+00:00"
}