{
  "symbol": "ETH",
  "name": "Ethereum",
  "price": 2322.73,
  "change_24h": 1.56,
  "market_cap": 280410695909.523,
  "rsi": 39.21,
  "analysis": {
    "elliott_wave": "ETH is in a corrective wave (B) within a larger bullish impulse, potentially nearing the end of its retracement.",
    "momentum": "The neutral RSI reading and recent price action suggest a stabilizing market, with momentum shifting in favor of bulls.",
    "key_levels": {
      "support": [
        "$2,200",
        "$2,100"
      ],
      "resistance": [
        "$2,400",
        "$2,550"
      ]
    },
    "trend_bias": "bullish",
    "trade_plan": "Buy on dips towards $2,200, targeting $2,400-$2,550 resistance zone. Set stop-loss at $2,100. Monitor for potential bearish reversal if price fails to hold above $2,200.",
    "risk_note": "Key risk: a sharp decline in market sentiment due to macroeconomic factors or regulatory changes."
  },
  "updated_at": "2026-04-29T07:56:32.215986+00:00"
}