{
  "symbol": "ETH",
  "name": "Ethereum",
  "price": 2318.69,
  "change_24h": 0.36,
  "market_cap": 279633214189.42316,
  "rsi": 26.15,
  "analysis": {
    "elliott_wave": "ETH is currently in a corrective wave (4) within a larger bullish trend, with a potential wave 5 forming.",
    "momentum": "The RSI is oversold, indicating a potential bounce in price, but the 0.36% 24h change suggests a lack of momentum.",
    "key_levels": {
      "support": [
        "$2,150",
        "$2,000"
      ],
      "resistance": [
        "$2,400",
        "$2,600"
      ]
    },
    "trend_bias": "bullish",
    "trade_plan": "Buy on dips towards $2,150, targeting $2,400. Set stop-loss at $2,000. Monitor for a potential breakout above $2,600.",
    "risk_note": "A potential bearish reversal if the price fails to hold above $2,150."
  },
  "updated_at": "2026-04-25T07:58:16.327045+00:00"
}