{
  "symbol": "ETH",
  "name": "Ethereum",
  "price": 2332.6,
  "change_24h": -1.16,
  "market_cap": 281524011562.167,
  "rsi": 53.3,
  "analysis": {
    "elliott_wave": "ETH is in a corrective wave (B) within a larger bearish trend, potentially forming a double zigzag pattern.",
    "momentum": "Momentum is neutral, with a slight bearish bias due to the recent price drop, but the RSI reading of 53.3 suggests a potential reversal.",
    "key_levels": {
      "support": [
        "$2,250",
        "$2,100"
      ],
      "resistance": [
        "$2,400",
        "$2,550"
      ]
    },
    "trend_bias": "bearish",
    "trade_plan": "Short-term, consider selling at resistance levels around $2,400-$2,550. Medium-term, look for a potential reversal at the $2,250 support level. Be cautious of a potential break below $2,100.",
    "risk_note": "A break below $2,100 could lead to a more significant price drop, potentially targeting the $2,000 level."
  },
  "updated_at": "2026-04-17T04:39:08.740550+00:00"
}