{
  "symbol": "ETH",
  "name": "Ethereum",
  "price": 2288.0,
  "change_24h": -0.07,
  "market_cap": 276021829134.5059,
  "rsi": 43.66,
  "analysis": {
    "elliott_wave": "ETH is currently in a corrective wave within a larger bullish trend, potentially forming a bullish impulse wave.",
    "momentum": "The neutral RSI reading and minor price dip indicate a stable momentum, but a potential reversal could occur if the price breaks below the current support levels.",
    "key_levels": {
      "support": [
        "$2,150.00",
        "$2,000.00"
      ],
      "resistance": [
        "$2,400.00",
        "$2,550.00"
      ]
    },
    "trend_bias": "bullish",
    "trade_plan": "Buy on dips towards $2,150.00, targeting $2,400.00 resistance. Set stop-loss at $2,000.00. Monitor the price action for a potential breakout.",
    "risk_note": "A sudden increase in selling pressure could lead to a sharp price drop, targeting the $2,000.00 support level."
  },
  "updated_at": "2026-04-28T21:51:19.690052+00:00"
}