{
  "symbol": "SUI",
  "name": "SUI",
  "price": 0.953148,
  "change_24h": 1.18,
  "market_cap": 3767862016.64649,
  "rsi": 66.83,
  "analysis": {
    "elliott_wave": "The current wave count suggests a possible corrective wave (B) within a larger bullish trend, with a potential target at $1.05.",
    "momentum": "The RSI reading of 66.83 indicates a neutral momentum, with price action showing a slight upward bias, but caution is advised as the 24h change is relatively flat at 1.18%.",
    "key_levels": {
      "support": [
        "$0.90",
        "$0.85"
      ],
      "resistance": [
        "$1.00",
        "$1.05"
      ]
    },
    "trend_bias": "bullish",
    "trade_plan": "Consider buying on dips to $0.90, with a target of $1.05, and set a stop-loss at $0.85. Monitor the 24h change for signs of acceleration.",
    "risk_note": "A sudden increase in selling pressure could lead to a sharp decline, so be prepared to adjust the trade plan accordingly."
  },
  "updated_at": "2026-04-15T18:00:07.115095+00:00"
}