{
  "symbol": "SUI",
  "name": "SUI",
  "price": 0.907136,
  "change_24h": -0.01,
  "market_cap": 3584634653.2296205,
  "rsi": 42.2,
  "analysis": {
    "elliott_wave": "We're currently in a corrective wave (B) within a larger bullish trend. The wave pattern suggests a potential bounce.",
    "momentum": "The neutral RSI reading and minor price drop indicate a pause in the uptrend, but the momentum remains relatively strong.",
    "key_levels": {
      "support": [
        "$0.85",
        "$0.80"
      ],
      "resistance": [
        "$0.95",
        "$1.00"
      ]
    },
    "trend_bias": "neutral",
    "trade_plan": "Consider buying on dips to $0.85 or $0.80, targeting $1.00 resistance. Set a stop-loss at $0.80 to limit potential losses.",
    "risk_note": "A sudden drop below $0.80 could indicate a more significant trend reversal."
  },
  "updated_at": "2026-04-30T21:44:38.537338+00:00"
}