{
  "symbol": "SUI",
  "name": "SUI",
  "price": 0.975405,
  "change_24h": 2.51,
  "market_cap": 3855441864.255964,
  "rsi": 58.63,
  "analysis": {
    "elliott_wave": "The current wave count suggests a possible bullish impulse wave, with a potential continuation of the upward trend. However, a pullback to retest previous highs is also possible.",
    "momentum": "The RSI reading of 58.63 indicates a neutral momentum, with the price action showing a moderate increase over the past 24 hours. This suggests that the trend is still upward but may be losing steam.",
    "key_levels": {
      "support": [
        "$0.85",
        "$0.90"
      ],
      "resistance": [
        "$1.05",
        "$1.10"
      ]
    },
    "trend_bias": "bullish",
    "trade_plan": "Buy on dips to $0.85, targeting $1.05. Set a stop-loss at $0.90. Consider scaling out of positions if the price reaches $1.05.",
    "risk_note": "A potential bearish reversal could occur if the price fails to hold above $0.90."
  },
  "updated_at": "2026-04-16T15:16:32.848137+00:00"
}