{
  "symbol": "SUI",
  "name": "SUI",
  "price": 0.938756,
  "change_24h": -3.01,
  "market_cap": 3710376843.892633,
  "rsi": 48.7,
  "analysis": {
    "elliott_wave": "The current wave count suggests a minor correction within a larger bullish trend. The price action indicates a potential wave 2 or 3 in the Elliott Wave theory.",
    "momentum": "The RSI reading of 48.7 indicates a neutral momentum, with the price action showing a slight bearish bias. However, the 24h change of -3.01% is relatively mild, suggesting a potential bounce.",
    "key_levels": {
      "support": [
        "$0.85",
        "$0.80"
      ],
      "resistance": [
        "$1.00",
        "$1.05"
      ]
    },
    "trend_bias": "neutral",
    "trade_plan": "Consider buying on a bounce above $0.90, targeting $1.00. Alternatively, sell on a break below $0.85, targeting $0.80. Monitor the price action for a clear trend bias.",
    "risk_note": "A break below $0.80 could indicate a more significant bearish trend reversal."
  },
  "updated_at": "2026-04-23T12:56:04.907508+00:00"
}