{
  "symbol": "SUI",
  "name": "SUI",
  "price": 0.954456,
  "change_24h": 1.41,
  "market_cap": 3773528537.294541,
  "rsi": 56.37,
  "analysis": {
    "elliott_wave": "We are currently in a minor corrective wave within a larger bullish trend. The wave count suggests a potential bullish impulse wave.",
    "momentum": "The RSI of 56.37 indicates a neutral momentum, but the 1.41% 24h change suggests a slight bullish bias. The price action is stable, but a breakout above $0.95 could lead to further gains.",
    "key_levels": {
      "support": [
        "$0.92",
        "$0.88"
      ],
      "resistance": [
        "$0.98",
        "$1.02"
      ]
    },
    "trend_bias": "bullish",
    "trade_plan": "Buy on dips above $0.92 with a target of $1.02. Set a stop-loss at $0.88 to limit potential losses. Monitor the price action for a breakout above $0.98.",
    "risk_note": "A sudden drop in market cap or a sharp decline in price could lead to a bearish reversal."
  },
  "updated_at": "2026-04-22T20:56:19.687067+00:00"
}