{
  "symbol": "SUI",
  "name": "SUI",
  "price": 0.890431,
  "change_24h": 5.34,
  "market_cap": 3522660288.6702075,
  "rsi": 62.12,
  "analysis": {
    "elliott_wave": "We are currently in a minor corrective wave (4) within a larger bullish trend, as the price action suggests a potential completion of the wave 4 and a subsequent bounce.",
    "momentum": "The RSI reading of 62.12 indicates a neutral momentum, but the 5.34% 24h price increase suggests a slight bullish bias, which may lead to further price appreciation.",
    "key_levels": {
      "support": [
        "$0.85",
        "$0.80"
      ],
      "resistance": [
        "$0.92",
        "$0.95"
      ]
    },
    "trend_bias": "bullish",
    "trade_plan": "Buy on dips towards $0.85, with a target of $0.95 and a stop-loss at $0.80. Monitor the price action for a potential breakout above $0.92.",
    "risk_note": "A potential bearish reversal could occur if the price action fails to break above $0.92 and instead forms a bearish engulfing candle."
  },
  "updated_at": "2026-04-06T22:23:16.226366+00:00"
}