{
  "symbol": "SUI",
  "name": "SUI",
  "price": 0.909467,
  "change_24h": -4.5,
  "market_cap": 3596463929.708506,
  "rsi": 39.29,
  "analysis": {
    "elliott_wave": "The current wave count suggests a potential bearish impulse wave (3) unfolding, with a possible correction in the near term.",
    "momentum": "The neutral RSI reading and recent price action indicate a lack of clear momentum, making it a range-bound market.",
    "key_levels": {
      "support": [
        "$0.85",
        "$0.80"
      ],
      "resistance": [
        "$0.95",
        "$1.00"
      ]
    },
    "trend_bias": "neutral",
    "trade_plan": "Consider a range-bound trading strategy, focusing on buying dips around $0.85 and selling rallies around $0.95.",
    "risk_note": "Key risk: a potential break below $0.80 could trigger a more significant bearish move."
  },
  "updated_at": "2026-04-12T21:22:57.780854+00:00"
}