{
  "symbol": "XAU",
  "name": "Gold",
  "price": 4793.16,
  "change_24h": -0.84,
  "market_cap": 0,
  "rsi": 51.29,
  "analysis": {
    "elliott_wave": "No applicable wave count due to gold's unique market dynamics, focusing on classical technical patterns and macro drivers.",
    "momentum": "Neutral momentum, with a 14-period RSI of 51.29, indicating a balanced market with no clear trend bias.",
    "key_levels": {
      "support": [
        "$4,037.68",
        "$3,408.28"
      ],
      "resistance": [
        "$5,357.81",
        "$6,048.54"
      ]
    },
    "trend_bias": "neutral",
    "trade_plan": "Consider buying on dips towards the TV Pivot Support levels, with a target of $5,357.81. Monitor the 24h change and adjust the trade plan accordingly. A stop-loss below $4,037.68 is recommended.",
    "risk_note": "A sharp increase in the DXY could lead to a decline in gold prices, making it essential to monitor the US Dollar's performance."
  },
  "updated_at": "2026-04-20T09:30:40.418151+00:00"
}