{
  "symbol": "XAU",
  "name": "Gold",
  "price": 4616.15,
  "change_24h": -0.12,
  "market_cap": 0,
  "rsi": 42.88,
  "analysis": {
    "elliott_wave": "No applicable Elliott Wave pattern assessment due to gold's unique market behavior.",
    "momentum": "Neutral momentum with the RSI at 42.88, indicating a potential consolidation phase. The 24h price change of -0.12% suggests a slight downtrend.",
    "key_levels": {
      "support": [
        "$4,458.09",
        "$4,294.63"
      ],
      "resistance": [
        "$4,837.22",
        "$5,052.89"
      ]
    },
    "trend_bias": "bearish",
    "trade_plan": "Consider shorting gold with a target of $4,294.63, or waiting for a breakout above $4,837.22 to enter a long position. Monitor the 24h price action for potential reversals.",
    "risk_note": "A significant shift in central bank policy or a sharp decline in the US dollar could lead to a safe-haven demand surge, potentially reversing the current bearish trend."
  },
  "updated_at": "2026-05-02T10:40:05.265793+00:00"
}