{
  "symbol": "XAU",
  "name": "Gold",
  "price": 4749.09,
  "change_24h": -0.34,
  "market_cap": 0,
  "rsi": 49.51,
  "analysis": {
    "elliott_wave": "Not applicable to gold due to its distinct market behavior",
    "momentum": "Neutral momentum with RSI at 49.51, but recent price action suggests a slight bearish tilt",
    "key_levels": {
      "support": [
        "$4,037.68",
        "$3,408.28"
      ],
      "resistance": [
        "$5,357.81",
        "$6,048.54"
      ]
    },
    "trend_bias": "neutral",
    "trade_plan": "Consider buying on dips towards the TV Pivot Support levels, with a target of retesting the 24h high. However, be cautious of a potential breakdown below the support levels. Monitor the price action closely for a clear direction.",
    "risk_note": "A sharp increase in the DXY or a significant rise in real yields could lead to a safe-haven demand shift, potentially weakening gold prices"
  },
  "updated_at": "2026-04-11T21:22:03.846790+00:00"
}