{
  "channel": "More Crypto Online",
  "channel_url": "https://www.youtube.com/@morecryptoonline",
  "updated_at": "2026-05-06T10:54:05.693761+00:00",
  "videos": [
    {
      "id": "vzSTuzHhAwU",
      "title": "Solana Chart Analysis: Will SOL Breakout Soon?",
      "published": "2026-05-06T05:30:24+00:00",
      "thumbnail": "https://i.ytimg.com/vi/vzSTuzHhAwU/hqdefault.jpg",
      "description": "Solana continues to follow Bitcoin higher but is significantly weaker. Bitcoin has already broken above the March highs while Solana would still need a 12 percent move just to get there. In this video",
      "url": "https://www.youtube.com/watch?v=vzSTuzHhAwU",
      "assets": [
        "other"
      ]
    },
    {
      "id": "vSolC7xaqd8",
      "title": "Is Solana Going to Break Out Soon?",
      "published": "2026-05-06T03:52:58+00:00",
      "thumbnail": "https://i.ytimg.com/vi/vSolC7xaqd8/hqdefault.jpg",
      "description": "Solana continues to follow Bitcoin higher but is significantly weaker. Bitcoin has already broken above the March highs while Solana would still need a 12 percent move just to get there. In this video",
      "url": "https://www.youtube.com/watch?v=vSolC7xaqd8",
      "assets": [
        "other"
      ]
    },
    {
      "id": "JbAznIqNtMw",
      "title": "Is Solana Going to Break Out Soon?",
      "published": "2026-05-06T02:49:08+00:00",
      "thumbnail": "https://i.ytimg.com/vi/JbAznIqNtMw/hqdefault.jpg",
      "description": "Solana continues to follow Bitcoin higher but is significantly weaker. Bitcoin has already broken above the March highs while Solana would still need a 12 percent move just to get there. In this video",
      "url": "https://www.youtube.com/watch?v=JbAznIqNtMw",
      "assets": [
        "other"
      ]
    },
    {
      "id": "eFcn3H2_y5w",
      "title": "Bitcoin Risk Analysis: Higher Risk at Resistance",
      "published": "2026-05-05T22:30:10+00:00",
      "thumbnail": "https://i.ytimg.com/vi/eFcn3H2_y5w/hqdefault.jpg",
      "description": "Bitcoin has basically reached the target zone. The 82K level on the futures chart and the upper boundary of the trend channel are converging as resistance. In this video I review the one-two setup fro",
      "url": "https://www.youtube.com/watch?v=eFcn3H2_y5w",
      "assets": [
        "btc"
      ]
    },
    {
      "id": "Rbs2Mgd3ccw",
      "title": "Bitcoin Target Zone Reached: Upside Potential & Risk",
      "published": "2026-05-05T21:15:03+00:00",
      "thumbnail": "https://i.ytimg.com/vi/Rbs2Mgd3ccw/hqdefault.jpg",
      "description": "Bitcoin has basically reached the target zone. The 82K level on the futures chart and the upper boundary of the trend channel are converging as resistance. In this video I review the one-two setup fro",
      "url": "https://www.youtube.com/watch?v=Rbs2Mgd3ccw",
      "assets": [
        "btc"
      ]
    },
    {
      "id": "qVG0A8fniGo",
      "title": "Bitcoin Analysis: Target Zone Reached, How Much Higher?",
      "published": "2026-05-05T18:51:50+00:00",
      "thumbnail": "https://i.ytimg.com/vi/qVG0A8fniGo/hqdefault.jpg",
      "description": "Bitcoin has basically reached the target zone. The 82K level on the futures chart and the upper boundary of the trend channel are converging as resistance. In this video I review the one-two setup fro",
      "url": "https://www.youtube.com/watch?v=qVG0A8fniGo",
      "assets": [
        "btc"
      ]
    },
    {
      "id": "NsDCk6NY_W4",
      "title": "Bitcoin Analysis: Target Zone Reached, How Much Higher?",
      "published": "2026-05-05T14:32:41+00:00",
      "thumbnail": "https://i.ytimg.com/vi/NsDCk6NY_W4/hqdefault.jpg",
      "description": "Bitcoin has basically reached the target zone. The 82K level on the futures chart and the upper boundary of the trend channel are converging as resistance. In this video I review the one-two setup fro",
      "url": "https://www.youtube.com/watch?v=NsDCk6NY_W4",
      "assets": [
        "btc"
      ]
    }
  ]
}